abc_tsp/ArtificialBeeColony_TSP.py
abc_tsp/__init__.py
abc_tsp-2.0.3.dist-info/LICENSE
abc_tsp-2.0.3.dist-info/METADATA
abc_tsp-2.0.3.dist-info/WHEEL
abc_tsp-2.0.3.dist-info/top_level.txt
abc_tsp-2.0.3.dist-info/RECORD
