Metadata-Version: 2.1
Name: abc_tsp
Version: 2.0.3
Summary: Artificial Bee Colony TSP solver
Home-page: https://github.com/AngelS017/ABC-algorithm-for-TSP
Author: Angel Sanz Gutierrez
Author-email: sanzangel017@gmail.com
License: MIT
Keywords: Artificial Bee Colony,ABC,Optimizer,TSP,k-opt,metaheuristic
Classifier: Programming Language :: Python :: 3
Classifier: License :: OSI Approved :: MIT License
Classifier: Operating System :: OS Independent
Requires-Python: >=3.8
License-File: LICENSE
Requires-Dist: numpy >=1.22
Requires-Dist: tqdm
Requires-Dist: joblib
Requires-Dist: numba
